topsis_manya/__init__.py
topsis_manya/topsis.py
topsis_manya_102203284-1.0.0.dist-info/LICENSE
topsis_manya_102203284-1.0.0.dist-info/METADATA
topsis_manya_102203284-1.0.0.dist-info/WHEEL
topsis_manya_102203284-1.0.0.dist-info/top_level.txt
topsis_manya_102203284-1.0.0.dist-info/RECORD
