Metadata-Version: 2.1
Name: topsis-manya-102203284
Version: 1.0.0
Summary: A Python package to implement TOPSIS for decision-making problems.
Home-page: https://github.com/manyaverma11/topsis-manya-102203284
Author: Manya Verma
Author-email: manyaverma0154@gmail.com
Classifier: Programming Language :: Python :: 3
Classifier: License :: OSI Approved :: MIT License
Classifier: Operating System :: OS Independent
Requires-Python: >=3.6
License-File: LICENSE
Requires-Dist: pandas
Requires-Dist: numpy
